streamlit_apexjs/__init__.py
streamlit_apexjs/frontend/build/asset-manifest.json
streamlit_apexjs/frontend/build/bootstrap.min.css
streamlit_apexjs/frontend/build/index.html
streamlit_apexjs/frontend/build/lime.min.css
streamlit_apexjs/frontend/build/static/js/2.a995fe0c.chunk.js
streamlit_apexjs/frontend/build/static/js/2.a995fe0c.chunk.js.LICENSE.txt
streamlit_apexjs/frontend/build/static/js/2.a995fe0c.chunk.js.map
streamlit_apexjs/frontend/build/static/js/main.20722192.chunk.js
streamlit_apexjs/frontend/build/static/js/main.20722192.chunk.js.map
streamlit_apexjs/frontend/build/static/js/main.e1cc847d.chunk.js
streamlit_apexjs/frontend/build/static/js/main.e1cc847d.chunk.js.map
streamlit_apexjs/frontend/build/static/js/main.f6bc9fb5.chunk.js
streamlit_apexjs/frontend/build/static/js/main.f6bc9fb5.chunk.js.map
streamlit_apexjs/frontend/build/static/js/runtime-main.e7c80b7b.js
streamlit_apexjs/frontend/build/static/js/runtime-main.e7c80b7b.js.map
streamlit_apexjs-0.0.3.dist-info/LICENSE
streamlit_apexjs-0.0.3.dist-info/METADATA
streamlit_apexjs-0.0.3.dist-info/WHEEL
streamlit_apexjs-0.0.3.dist-info/top_level.txt
streamlit_apexjs-0.0.3.dist-info/RECORD
