Metadata-Version: 2.1
Name: streamlit_apexjs
Version: 0.0.3
Summary: streamlit_apexcharts React component for Streamlit
Home-page: https://github.com/drogbadvc/streamlit-apexcharts
Author: Andell
Author-email: drogadvc@gmail.com
License: UNKNOWN
Platform: UNKNOWN
Requires-Python: >=3.7
License-File: LICENSE
